Metadata-Version: 2.1
Name: nanorequests
Version: 1.0.2
Summary: The simplest REST requests package for quick API integration
Home-page: https://github.com/viralparmarme/nanorequests
Author: Viral Parmar
Author-email: viralparmarme@gmail.com
License: MIT
Keywords: nanorequests viralparmarme viralparmar
Platform: UNKNOWN
License-File: LICENSE.txt
